Workbook

Sheet BD_Config
A1: ID_Mat | B1: Nombre Papel | C1: Costo Pliego | D1: ID_Mq | E1: Nombre Maquina | F1: Tecnología | G1: $ Arreglo | H1: $ Variable | I1: Columna 9 | J1: Columna 10 | K1: ID_Ter | L1: Nombre Proceso | M1: Tipo | N1: $ Arreglo 2 | O1: $ Variable 2
A2: P-01 | B2: Propalcote 150g | C2: 400 | D2: MQ-01 | E2: Heidelberg Speedmaster | F2: Offset | G2: 180000 | H2: 45000 | K2: T-01 | L2: Troquelado (ZDM) | M2: Millar | N2: 50000 | O2: 25000
A3: P-02 | B3: Propalcote 300g | C3: 800 | D3: MQ-02 | E3: Heidelberg GTO | F3: Offset | G3: 80000 | H3: 30000 | K3: T-02 | L3: Plastificado Mate | M3: Pliego | N3: 0 | O3: 450
A4: P-03 | B4: Bond 75g | C4: 120 | D4: MQ-03 | E4: Ricoh Pro C7100x | F4: Digital | G4: 0 | H4: 600 | K4: T-03 | L4: Plegado Auto | M4: Millar | N4: 30000 | O4: 10000
A5: P-04 | B5: Adhesivo | C5: 2500 | D5: MQ-04 | E5: Plotter Stormjet | F5: Gran Formato | G5: 0 | H5: 25000 | K5: T-04 | L5: Refile / Corte | M5: Global | N5: 15000 | O5: 0
A6: P-05 | B6: Maule C18 | C6: 1800 | D6: MQ-05 | E6: UV DTF | F6: Gran Formato | G6: 0 | H6: 55000 | K6: T-05 | L6: Pegue a Mano | M6: Unidad | N6: 0 | O6: 80
K7: T-06 | L7: Diseño / Arte | M7: Global | N7: 50000 | O7: 0
G9: F

Sheet IN_Cotizacion
A1: No. Cotización | B1: Columna 1
A2: Fecha | B2: =TODAY() -> 46090
A3: Cliente
A4: Producto
A5: Cantidad Deseada | B5: 5000
A8: Papel Seleccionado | B8: Costo Papel Unit | C8: Cabida (x Pliego) | D8: Pliegos Requeridos | E8: % Merma | F8: Total a Comprar | G8: SUBTOTAL PAPEL
A9: Propalcote 300g | B9: =IFERROR(VLOOKUP(A9, BD_Config!B:C, 2, FALSE), 0) -> 800 | C9: 16 | D9: =IF(C9>0, ROUNDUP($B$5/C9, 0), 0) -> 313 | E9: 0.05 | F9: =ROUNDUP(D9 * (1 + E9), 0) -> 329 | G9: =F9 * B9 -> 263200
A11: MEDIDAS PROD | B11: MEDIDAS PAPEL | C11: CABIDA | D11: PAPEL TOTAL | E11: Manual | F11: FINAL
A12: Alto (cm) | B12: Ancho (cm) | C12: Alto (cm) | D12: Ancho (cm)
A13: 25 | B13: 15 | C13: 70 | D13: 100 | F13: =IF(E13<>"", E13, IF(OR(A13=0, B13=0), 0, MAX(INT(C13/A13)*INT(D13/B13), INT(C13/B13)*INT(D13/A13)))) -> 16
A15: PAPEL: | C15: Costo Unit: | D15: $ 400 | E15: Total Pliegos: | F15: =IF(F13>0, ROUNDUP(($B$5/F13)*1.1, 0), 0) -> 344
A18: Máquina | B18: Tecnología | C18: Tarifa Arreglo | D18: Tarifa Variable | E18: Tintas / Cambios | F18: SUBTOTAL IMPRESIÓN
A19: Plotter Stormjet | B19: =IFERROR(VLOOKUP(A19, BD_Config!E:H, 2, FALSE), "") -> Gran Formato | C19: =IFERROR(VLOOKUP(A19, BD_Config!E:H, 3, FALSE), 0) -> 0 | D19: =IFERROR(VLOOKUP(A19, BD_Config!E:H, 4, FALSE), 0) -> 25000 | E19: 5 | F19: =IF(B19="Offset", (C19*E19) + ((F9/1000)*D19), IF(B19="Digital", F9*D19, IF(B19="Gran Formato", F9*D19, 0) ) ) -> 8225000
A22: Proceso | B22: Detalle | C22: Cantidad Base | D22: Costo Calc.
A23: Plastificado Mate | C23: =IF(A23="", "", IF(ISNUMBER(SEARCH("Plastificado", A23)), $F$9, $B$5)) -> 329 | D23: =IFERROR( LET( tipo, VLOOKUP(A23, BD_Config!L:O, 2, 0), fijo, VLOOKUP(A23, BD_Config!L:O, 3, 0), var, VLOOKUP(A23, BD_Config!L:O, 4, 0), cant, C23, IF(tipo="Millar", fijo + ((cant/1000)*var), IF(tipo="Global", fijo, (cant * var) + fijo ) ) ), 0) -> 148050
A24: Troquelado (ZDM) | C24: =IF(A24="", "", IF(ISNUMBER(SEARCH("Plastificado", A24)), $F$9, $B$5)) -> 5000 | D24: =IFERROR( LET( tipo, VLOOKUP(A24, BD_Config!L:O, 2, 0), fijo, VLOOKUP(A24, BD_Config!L:O, 3, 0), var, VLOOKUP(A24, BD_Config!L:O, 4, 0), cant, C24, IF(tipo="Millar", fijo + ((cant/1000)*var), IF(tipo="Global", fijo, (cant * var) + fijo ) ) ), 0) -> 175000
A25: Pegue a Mano | C25: =IF(A25="", "", IF(ISNUMBER(SEARCH("Plastificado", A25)), $F$9, $B$5)) -> 5000 | D25: =IFERROR( LET( tipo, VLOOKUP(A25, BD_Config!L:O, 2, 0), fijo, VLOOKUP(A25, BD_Config!L:O, 3, 0), var, VLOOKUP(A25, BD_Config!L:O, 4, 0), cant, C25, IF(tipo="Millar", fijo + ((cant/1000)*var), IF(tipo="Global", fijo, (cant * var) + fijo ) ) ), 0) -> 400000
C26: =IF(A26="", "", IF(ISNUMBER(SEARCH("Plastificado", A26)), $F$9, $B$5)) | D26: =IFERROR( LET( tipo, VLOOKUP(A26, BD_Config!L:O, 2, 0), fijo, VLOOKUP(A26, BD_Config!L:O, 3, 0), var, VLOOKUP(A26, BD_Config!L:O, 4, 0), cant, C26, IF(tipo="Millar", fijo + ((cant/1000)*var), IF(tipo="Global", fijo, (cant * var) + fijo ) ) ), 0) -> 0
C27: =IF(A27="", "", IF(ISNUMBER(SEARCH("Plastificado", A27)), $F$9, $B$5)) | D27: =IFERROR( LET( tipo, VLOOKUP(A27, BD_Config!L:O, 2, 0), fijo, VLOOKUP(A27, BD_Config!L:O, 3, 0), var, VLOOKUP(A27, BD_Config!L:O, 4, 0), cant, C27, IF(tipo="Millar", fijo + ((cant/1000)*var), IF(tipo="Global", fijo, (cant * var) + fijo ) ) ), 0) -> 0
C28: =IF(A28="", "", IF(ISNUMBER(SEARCH("Plastificado", A28)), $F$9, $B$5)) | D28: =IFERROR( LET( tipo, VLOOKUP(A28, BD_Config!L:O, 2, 0), fijo, VLOOKUP(A28, BD_Config!L:O, 3, 0), var, VLOOKUP(A28, BD_Config!L:O, 4, 0), cant, C28, IF(tipo="Millar", fijo + ((cant/1000)*var), IF(tipo="Global", fijo, (cant * var) + fijo ) ) ), 0) -> 0
C29: =IF(A29="", "", IF(ISNUMBER(SEARCH("Plastificado", A29)), $F$9, $B$5)) | D29: =IFERROR( LET( tipo, VLOOKUP(A29, BD_Config!L:O, 2, 0), fijo, VLOOKUP(A29, BD_Config!L:O, 3, 0), var, VLOOKUP(A29, BD_Config!L:O, 4, 0), cant, C29, IF(tipo="Millar", fijo + ((cant/1000)*var), IF(tipo="Global", fijo, (cant * var) + fijo ) ) ), 0) -> 0
C30: =IF(A30="", "", IF(ISNUMBER(SEARCH("Plastificado", A30)), $F$9, $B$5)) | D30: =IFERROR( LET( tipo, VLOOKUP(A30, BD_Config!L:O, 2, 0), fijo, VLOOKUP(A30, BD_Config!L:O, 3, 0), var, VLOOKUP(A30, BD_Config!L:O, 4, 0), cant, C30, IF(tipo="Millar", fijo + ((cant/1000)*var), IF(tipo="Global", fijo, (cant * var) + fijo ) ) ), 0) -> 0
C31: =IF(A31="", "", IF(ISNUMBER(SEARCH("Plastificado", A31)), $F$9, $B$5)) | D31: =IFERROR( LET( tipo, VLOOKUP(A31, BD_Config!L:O, 2, 0), fijo, VLOOKUP(A31, BD_Config!L:O, 3, 0), var, VLOOKUP(A31, BD_Config!L:O, 4, 0), cant, C31, IF(tipo="Millar", fijo + ((cant/1000)*var), IF(tipo="Global", fijo, (cant * var) + fijo ) ) ), 0) -> 0
A33: Totales | B33: Valor | C33: Costo Con Margen de Ganacia
A34: Total Materiales | B34: =G9 -> 263200
A35: Total Impresión | B35: =F19 -> 8225000
A36: Total Terminados | B36: =SUM(D23:D31) -> 723050
A37: Costo total sin Margen de Ganancia | B37: =SUM(B34:B36) -> 9211250
A38: Margen (%) | B38: 0.25 | C38: =IF(B38 < 1, B37 / (1 - B38), "Error: Margen > 100%") -> 12281667
A39: Precio Venta | B39: =B37 / (1 - B38) -> 12281667
A40: Precio Unitario | B40: =B39 / $B$5 -> 2456.3333
A41: IVA | B41: =(B39*0.19) -> 2333516.7
A42: Precio Total + IVA | B42: =(B41+B39) -> 14615183
A45: Trabajos Digitales / Rápidos: Usa márgenes altos (40% - 60%) porque son montos pequeños.
A46: Trabajos Offset / Volumen: Usa márgenes medios (25% - 35%) para ser competitivo.
A47: Revendedores: Usa márgenes bajos (15% - 20%) porque te traen volumen constante.
